mf_excel/cli.py
mf_excel/backend/app.py
mf_excel/backend/services/__init__.py
mf_excel/backend/services/config.py
mf_excel/backend/services/forecast_service.py
mf_excel/backend/services/validation.py
mf_excel/excel_client/__init__.py
mf_excel/excel_client/addin.py
mf_excel/excel_client/config.py
mf_excel/excel_client/ui.py
mf_excel-0.1.2.dist-info/METADATA
mf_excel-0.1.2.dist-info/WHEEL
mf_excel-0.1.2.dist-info/entry_points.txt
mf_excel-0.1.2.dist-info/top_level.txt
mf_excel-0.1.2.dist-info/RECORD
