Metadata-Version: 2.4
Name: mf-excel
Version: 0.1.2
Summary: An Excel Integration for macroframe-forecast
Author: Yusuf Muhammed Adekunle
License: MIT
Requires-Python: >=3.9
Requires-Dist: pandas==2.2.2
Requires-Dist: flask==3.0.0
Requires-Dist: sktime==0.28.0
Requires-Dist: scikit-learn==1.4.2
Requires-Dist: macroframe-forecast==0.1.5
Requires-Dist: xlwings==0.33.15
Requires-Dist: requests==2.32.3
Requires-Dist: dask[dataframe]==2024.8.1
Requires-Dist: simplejson==3.20.2
